LICENSE
README.md
setup.py
pm2case.egg-info/PKG-INFO
pm2case.egg-info/SOURCES.txt
pm2case.egg-info/dependency_links.txt
pm2case.egg-info/entry_points.txt
pm2case.egg-info/top_level.txt
postman2case/__init__.py
postman2case/cli.py
postman2case/compat.py
postman2case/core.py
postman2case/parser.py
tests/__init__.py
tests/test_postmanparser.py