Metadata-Version: 2.1
Name: pm2case
Version: 0.0.6
Summary: Convert POSTMAN data to JSON testcases for HttpRunner.
Home-page: https://github.com/HttpRunner/postman2case
Author: luguo
Author-email: hluguoj@163.com
License: MIT
Keywords: postman converter json
Platform: UNKNOWN
Classifier: Development Status :: 3 - Alpha
Classifier: Programming Language :: Python :: 3.5
Classifier: Programming Language :: Python :: 3.6
Classifier: Programming Language :: Python :: 3.7
Classifier: Programming Language :: Python :: 3.8
Classifier: Programming Language :: Python :: 3.9
